easyfrenchtax/__init__.py
easyfrenchtax/stock_helper.py
easyfrenchtax/tax_simulator.py
easyfrenchtax-0.1.1.dist-info/licenses/LICENSE
easyfrenchtax-0.1.1.dist-info/METADATA
easyfrenchtax-0.1.1.dist-info/WHEEL
easyfrenchtax-0.1.1.dist-info/top_level.txt
easyfrenchtax-0.1.1.dist-info/RECORD
