Metadata-Version: 2.4
Name: easyfrenchtax
Version: 0.1.1
Summary: A simulator of French taxes
Home-page: https://github.com/had/easyfrenchtax
Author: Hadrien Hamel
Author-email: hadrien.hamel@gmail.com
License: MIT
Project-URL: Bug Tracker, https://github.com/had/easyfrenchtax/issues
Classifier: Programming Language :: Python :: 3
Classifier: Development Status :: 3 - Alpha
Classifier: Operating System :: OS Independent
Classifier: Topic :: Software Development :: Libraries
Classifier: Topic :: Office/Business :: Financial
Classifier: Topic :: Office/Business :: Financial :: Investment
Requires-Python: >=3.8.2
License-File: LICENSE
Requires-Dist: currencyconverter
Dynamic: license-file
